wilds/__init__.py
wilds/download_datasets.py
wilds/get_dataset.py
wilds/version.py
wilds/common/__init__.py
wilds/common/data_loaders.py
wilds/common/grouper.py
wilds/common/utils.py
wilds/common/metrics/__init__.py
wilds/common/metrics/all_metrics.py
wilds/common/metrics/loss.py
wilds/common/metrics/metric.py
wilds/datasets/__init__.py
wilds/datasets/amazon_dataset.py
wilds/datasets/bdd100k_dataset.py
wilds/datasets/camelyon17_dataset.py
wilds/datasets/celebA_dataset.py
wilds/datasets/civilcomments_dataset.py
wilds/datasets/domainnet_dataset.py
wilds/datasets/download_utils.py
wilds/datasets/encode_dataset.py
wilds/datasets/fmow_dataset.py
wilds/datasets/globalwheat_dataset.py
wilds/datasets/iwildcam_dataset.py
wilds/datasets/ogbmolpcba_dataset.py
wilds/datasets/poverty_dataset.py
wilds/datasets/py150_dataset.py
wilds/datasets/rxrx1_dataset.py
wilds/datasets/sqf_dataset.py
wilds/datasets/waterbirds_dataset.py
wilds/datasets/wilds_dataset.py
wilds/datasets/yelp_dataset.py
wilds/datasets/archive/__init__.py
wilds/datasets/archive/fmow_v1_0_dataset.py
wilds/datasets/archive/iwildcam_v1_0_dataset.py
wilds/datasets/archive/poverty_v1_0_dataset.py
wilds/datasets/unlabeled/__init__.py
wilds/datasets/unlabeled/amazon_unlabeled_dataset.py
wilds/datasets/unlabeled/camelyon17_unlabeled_dataset.py
wilds/datasets/unlabeled/civilcomments_unlabeled_dataset.py
wilds/datasets/unlabeled/domainnet_unlabeled_dataset.py
wilds/datasets/unlabeled/fmow_unlabeled_dataset.py
wilds/datasets/unlabeled/globalwheat_unlabeled_dataset.py
wilds/datasets/unlabeled/iwildcam_unlabeled_dataset.py
wilds/datasets/unlabeled/ogbmolpcba_unlabeled_dataset.py
wilds/datasets/unlabeled/poverty_unlabeled_dataset.py
wilds/datasets/unlabeled/wilds_unlabeled_dataset.py
wilds-2.0.0.dist-info/LICENSE
wilds-2.0.0.dist-info/METADATA
wilds-2.0.0.dist-info/WHEEL
wilds-2.0.0.dist-info/top_level.txt
wilds-2.0.0.dist-info/RECORD
