Metadata-Version: 2.1
Name: wilds
Version: 2.0.0
Summary: WILDS distribution shift benchmark
Home-page: https://wilds.stanford.edu
Author: WILDS team
Author-email: wilds@cs.stanford.edu
License: MIT
Platform: UNKNOWN
Classifier: Topic :: Scientific/Engineering :: Artificial Intelligence
Classifier: Intended Audience :: Science/Research
Classifier: Programming Language :: Python :: 3
Classifier: License :: OSI Approved :: MIT License
Requires-Python: >=3.6
Requires-Dist: numpy (>=1.19.1)
Requires-Dist: ogb (>=1.2.6)
Requires-Dist: outdated (>=0.2.0)
Requires-Dist: pandas (>=1.1.0)
Requires-Dist: pillow (>=7.2.0)
Requires-Dist: pytz (>=2020.4)
Requires-Dist: torch (>=1.7.0)
Requires-Dist: torchvision (>=0.8.2)
Requires-Dist: tqdm (>=4.53.0)
Requires-Dist: scikit-learn (>=0.20.0)
Requires-Dist: scipy (>=1.5.4)
